pguid/__init__.py
pguid/main.py
pguid-0.0.9.dist-info/METADATA
pguid-0.0.9.dist-info/WHEEL
pguid-0.0.9.dist-info/top_level.txt
pguid-0.0.9.dist-info/RECORD
