Metadata-Version: 2.1
Name: pguid
Version: 0.0.9
Requires-Dist: pygame>=1.9.1
Requires-Dist: requests>=2.0.0
